{
  "discussion": "https://groups.google.com/forum/#!topic/tosdr/t-INoE6fH98",
  "id": "t-INoE6fH98",
  "license-for-this-file": "This work is licensed under the Creative Commons Attribution-ShareAlike 3.0 Unported License. To view a copy of this license, visit http://creativecommons.org/licenses/by-sa/3.0/ or send a letter to Creative Commons, 444 Castro Street, Suite 900, Mountain View, California, 94041, .USA",
  "services": [
    "delicious"
  ],
  "source": "http://www.delicious.com/terms",
  "title": "Licencia de Copyright de tu contenido demasiado amplia, incluye el derecho de Delicious distribuir por cualquier medio",
  "topics": [
    "copyright-scope"
  ],
  "tosdr": {
    "binding": true,
    "case": "broad license including right to distribute through any media",
    "point": "bad",
    "score": 100,
    "tldr": "La licencia de copyright concedida a Delicious no esta limitada a la operatividad del servicio. Tu contenido puede ser explotado “por algunos o todos los medios y canales de distribucion (conocidos o por crear)” i.e. puede ser distribuido por Delicious fuera del servicio de Delicious."
  }
}