{
  "discussion": "https://groups.google.com/d/topic/tosdr/X99SUnV7RUs/discussion",
  "id": "X99SUnV7RUs",
  "meta": {
    "author": "ToS;DR by Unhosted",
    "contributors": [
      "Hugo Roy <hugo@unhosted.org>"
    ],
    "license-for-this-file": "This work is licensed under the Creative Commons Attribution-ShareAlike 3.0 Unported License. To view a copy of this license, visit http://creativecommons.org/licenses/by-sa/3.0/ or send a letter to Creative Commons, 444 Castro Street, Suite 900, Mountain View, California, 94041, .USA",
    "spec-version": "1.1"
  },
  "services": [
    "500px"
  ],
  "source": {
    "faq": "",
    "terms": "http://500px.com/terms"
  },
  "title": "Amplia licencia de copyright",
  "topics": [
    "copyright-scope"
  ],
  "tosdr": {
    "binding": true,
    "case": "broader than necessary",
    "point": "bad",
    "score": 50,
    "tldr": "La licencia de derechos de autor que usted otorga a 500px es transferible y sublicenciable. La licencia de derechos de autor es limitado para el uso “en relación con los Servicios” que incluye usos promocionales y de redistribución “a otros partidos, sitios web, aplicaciones y otras entidades” si se acreditan adecuadamente. La licencia de su contenido termina cuando se quita dicho contenido."
  }
}